heimr/__init__.py
heimr/analyzer.py
heimr/cli.py
heimr/comparator.py
heimr/detector.py
heimr/kpi.py
heimr/llm.py
heimr/loki.py
heimr/pdf_generator.py
heimr/prometheus.py
heimr/setup_llm.py
heimr/tempo.py
heimr/parsers/__init__.py
heimr/parsers/base.py
heimr/parsers/gatling.py
heimr/parsers/har.py
heimr/parsers/jtl.py
heimr/parsers/k6.py
heimr/parsers/locust.py
heimr_ai-0.1.0.dist-info/LICENSE
heimr_ai-0.1.0.dist-info/METADATA
heimr_ai-0.1.0.dist-info/WHEEL
heimr_ai-0.1.0.dist-info/entry_points.txt
heimr_ai-0.1.0.dist-info/top_level.txt
heimr_ai-0.1.0.dist-info/RECORD
