Metadata-Version: 2.1
Name: heimr-ai
Version: 0.1.0
Summary: AI-Powered Load Test Analysis & Root Cause Explanation
Home-page: https://heimr.ai
Author: Juan Estevez Castillo
Author-email: jd.estevezcastillo@gmail.com
Project-URL: Bug Tracker, https://github.com/jdestevezcastillo-perfeng/Heimr.ai/issues
Project-URL: Documentation, https://github.com/jdestevezcastillo-perfeng/Heimr.ai/blob/main/docs/WIKI.md
Project-URL: Source Code, https://github.com/jdestevezcastillo-perfeng/Heimr.ai
Keywords: load-testing,performance,jmeter,k6,gatling,locust,anomaly-detection,root-cause-analysis,llm,prometheus,observability
Classifier: Development Status :: 4 - Beta
Classifier: Intended Audience :: Developers
Classifier: Intended Audience :: System Administrators
Classifier: Topic :: Software Development :: Testing
Classifier: Topic :: System :: Monitoring
Classifier: License :: OSI Approved :: GNU Affero General Public License v3
Classifier: Programming Language :: Python :: 3
Classifier: Programming Language :: Python :: 3.8
Classifier: Programming Language :: Python :: 3.9
Classifier: Programming Language :: Python :: 3.10
Classifier: Programming Language :: Python :: 3.11
Classifier: Programming Language :: Python :: 3.12
Classifier: Operating System :: OS Independent
Requires-Python: >=3.8
License-File: LICENSE
Requires-Dist: numpy >=1.21.0
Requires-Dist: pandas >=1.5.0
Requires-Dist: pyyaml >=6.0
Requires-Dist: requests >=2.28.0
Provides-Extra: all
Requires-Dist: anthropic >=0.18.0 ; extra == 'all'
Requires-Dist: openai >=1.0.0 ; extra == 'all'
Provides-Extra: anthropic
Requires-Dist: anthropic >=0.18.0 ; extra == 'anthropic'
Provides-Extra: dev
Requires-Dist: black >=23.0.0 ; extra == 'dev'
Requires-Dist: flake8 >=6.0.0 ; extra == 'dev'
Requires-Dist: isort >=5.12.0 ; extra == 'dev'
Requires-Dist: mypy >=1.0.0 ; extra == 'dev'
Requires-Dist: pytest-cov >=4.0.0 ; extra == 'dev'
Requires-Dist: pytest >=7.0.0 ; extra == 'dev'
Provides-Extra: docs
Requires-Dist: mkdocs-material >=9.0.0 ; extra == 'docs'
Requires-Dist: mkdocs >=1.5.0 ; extra == 'docs'
Provides-Extra: llm
Requires-Dist: anthropic >=0.18.0 ; extra == 'llm'
Requires-Dist: openai >=1.0.0 ; extra == 'llm'
Provides-Extra: openai
Requires-Dist: openai >=1.0.0 ; extra == 'openai'
